{
  "_notes": "rev 7 (2026-07-17): NEW ART DIRECTION repaint - painterly-pixel iso town matching the tower/region-map art line (owner-approved candidate, style anchor for all future battle maps). Painted by Nano Banana at 1584x672 native (aspect 2.357 ~= the 2048x868 viewBox; renderer rescales, coordinates below stay in viewBox space). Post: sparkle removed at (1465,551), stray road cart removed at (224,331), grade B applied (meanV 0.403 -> 0.520). pixelArt:false - detailed art samples bilinear. Layout: one road, west gate -> market plaza (lane rides y~310 between stall row and smithy roof) -> covered bridge over the river (bridge-roof occluder hides unit tops crossing 'inside' it) -> east gate -> right edge. FIRST-PASS authoring by pixel inspection + ghost-walk verification; owner fine-tunes via ?author=1 drag+export. Old rev 6 art + authoring in git history.",
  "image": "frontier-town.png",
  "pixelArt": false,
  "viewBox": [
    0,
    0,
    2048,
    868
  ],
  "world": "verdant",
  "battleTheme": "town-gate",
  "nodeId": "start",
  "difficulty": "tutorial",
  "grid": {
    "cols": 30,
    "rows": 13
  },
  "lanes": [
    {
      "id": "main",
      "spawnEdge": "west",
      "waypoints": [
        [
          0,
          422
        ],
        [
          194,
          422
        ],
        [
          317,
          426
        ],
        [
          478,
          429
        ],
        [
          621,
          426
        ],
        [
          724,
          420
        ],
        [
          827,
          403
        ],
        [
          931,
          398
        ],
        [
          1060,
          398
        ],
        [
          1164,
          407
        ],
        [
          1235,
          421
        ],
        [
          1280,
          434
        ],
        [
          1358,
          437
        ],
        [
          1429,
          437
        ],
        [
          1500,
          431
        ],
        [
          1603,
          426
        ],
        [
          1720,
          424
        ],
        [
          1836,
          416
        ],
        [
          1939,
          411
        ],
        [
          2048,
          411
        ]
      ]
    }
  ],
  "leak": {
    "x": 2048,
    "y": 411,
    "landmark": "east road past the gate"
  },
  "buildSlots": [
    {
      "id": "s1",
      "x": 220,
      "y": 351,
      "pad": "open",
      "note": "outside west gate, north pad"
    },
    {
      "id": "s2",
      "x": 155,
      "y": 504,
      "pad": "open",
      "note": "outside west gate, south pad"
    },
    {
      "id": "s3",
      "x": 608,
      "y": 355,
      "pad": "open",
      "note": "inside gate, north pad"
    },
    {
      "id": "s4",
      "x": 511,
      "y": 514,
      "pad": "open",
      "note": "inside gate, south pad"
    },
    {
      "id": "s5",
      "x": 789,
      "y": 359,
      "pad": "open",
      "note": "market plaza worn patch"
    },
    {
      "id": "s6",
      "x": 1571,
      "y": 351,
      "pad": "open",
      "note": "west of east tower"
    },
    {
      "id": "s7",
      "x": 1842,
      "y": 351,
      "pad": "open",
      "note": "outside east gate, north pad"
    },
    {
      "id": "s8",
      "x": 1791,
      "y": 527,
      "pad": "open",
      "note": "outside east gate, south pad"
    }
  ],
  "occluders": [
    {
      "id": "west-gate-tower",
      "rect": [
        327,
        323,
        416,
        433
      ],
      "note": "tower body over lane"
    },
    {
      "id": "bridge-roof",
      "rect": [
        1271,
        394,
        1435,
        426
      ],
      "note": "covered-bridge top beam — units cross behind it"
    },
    {
      "id": "east-gate-tower",
      "rect": [
        1678,
        304,
        1769,
        506
      ],
      "note": "tower body over lane"
    },
    {
      "id": "east-house-roof-tip",
      "rect": [
        1545,
        407,
        1642,
        462
      ],
      "note": "gable peak poking into the lane band"
    }
  ]
}
